sardugame/__init__.py
sardugame/game.py
sardugame-0.4.1.dist-info/METADATA
sardugame-0.4.1.dist-info/WHEEL
sardugame-0.4.1.dist-info/top_level.txt
sardugame-0.4.1.dist-info/RECORD
