Metadata-Version: 2.1
Name: sardugame
Version: 0.4.1
Summary: un motore per crare giochi 2d
Home-page: https://github.com/giovanni/sardugame
Author: Giovanni
Author-email: cetriolonazionale@gmail.com
License: UNKNOWN
Platform: UNKNOWN
Classifier: Programming Language :: Python :: 3
Classifier: License :: OSI Approved :: MIT License
Classifier: Operating System :: OS Independent
Requires-Dist: pygame
